{
  "scenario": "S3_tight_regulation",
  "scenario_file": "config_qubo_S3.yaml",
  "seed": 1000,
  "N": 40,
  "M": 4,
  "K": 5,
  "L_reg_slack": 3,
  "n_total": 52,
  "qubo_file_used": "qubo_Q_S3_tight_regulation_N40.npz",
  "energy_greedy": -22274264.95524327,
  "energy_sa_best": -22274764.95524327,
  "raw_objective_greedy": 9704.504413159531,
  "raw_objective_sa_best": 9204.504413159531,
  "greedy_runtime_sec": 0.0314874,
  "sa_runtime_sec": 22.3539356,
  "total_classical_runtime_sec": 22.385423,
  "solvers": {
    "greedy": {
      "energy_total": -22274264.95524327,
      "raw_objective": 9704.504413159531,
      "decoded": {
        "chosen_deductible_band": 2,
        "chosen_premium_band": 3,
        "selected_features_count": 6,
        "selected_feature_ids": [
          3,
          8,
          16,
          26,
          31,
          35
        ],
        "selected_reg_features_count": 6
      },
      "violations": {
        "onehot_y": 0.0,
        "onehot_z": 0.0,
        "reg_shortfall": 0.0,
        "affordability_indicator": 0.0
      },
      "penalty_energy": {
        "penE_onehot": 0.0,
        "penE_reg": 0.0,
        "penE_afford": 0.0,
        "penE_total": 0.0
      },
      "constraint_checks": {
        "onehot_ok": true,
        "reg_satisfied": true,
        "reg_violation_amount": 0,
        "affordability_enabled": false,
        "affordability_disallow_bands": [],
        "affordability_satisfied": true,
        "affordability_violation": false,
        "is_feasible": true
      },
      "feasibility_margin": {
        "onehot_worst_violation": 0.0,
        "reg_shortfall": 0.0,
        "affordability_violated": false
      },
      "qubo_terms_signed": {
        "qterm_onehot_signed": -602269.4448555793,
        "qterm_reg_signed": -21681700.014800854,
        "qterm_afford_signed": 0.0,
        "qterm_total_signed": -22283969.459656432
      },
      "penalty_weights": {
        "A_onehot": 301134.72242778965,
        "B_reg": 602269.4448555793,
        "D_afford": 0.0
      },
      "energy_decomposition_check": {
        "reconstructed_energy": -22274264.955243275,
        "absolute_error": 3.725290298461914e-09,
        "relative_error": 1.6724638527678984e-16,
        "validation_passed": true
      },
      "params": {
        "multistart": true,
        "num_starts": 20,
        "random_seed": 104729001
      }
    },
    "sa": {
      "energy_total": -22274764.95524327,
      "raw_objective": 9204.504413159531,
      "decoded": {
        "chosen_deductible_band": 2,
        "chosen_premium_band": 5,
        "selected_features_count": 6,
        "selected_feature_ids": [
          3,
          8,
          16,
          26,
          31,
          35
        ],
        "selected_reg_features_count": 6
      },
      "violations": {
        "onehot_y": 0.0,
        "onehot_z": 0.0,
        "reg_shortfall": 0.0,
        "affordability_indicator": 0.0
      },
      "penalty_energy": {
        "penE_onehot": 0.0,
        "penE_reg": 0.0,
        "penE_afford": 0.0,
        "penE_total": 0.0
      },
      "constraint_checks": {
        "onehot_ok": true,
        "reg_satisfied": true,
        "reg_violation_amount": 0,
        "affordability_enabled": false,
        "affordability_disallow_bands": [],
        "affordability_satisfied": true,
        "affordability_violation": false,
        "is_feasible": true
      },
      "feasibility_margin": {
        "onehot_worst_violation": 0.0,
        "reg_shortfall": 0.0,
        "affordability_violated": false
      },
      "qubo_terms_signed": {
        "qterm_onehot_signed": -602269.4448555793,
        "qterm_reg_signed": -21681700.014800854,
        "qterm_afford_signed": 0.0,
        "qterm_total_signed": -22283969.459656432
      },
      "penalty_weights": {
        "A_onehot": 301134.72242778965,
        "B_reg": 602269.4448555793,
        "D_afford": 0.0
      },
      "energy_decomposition_check": {
        "reconstructed_energy": -22274764.955243275,
        "absolute_error": 3.725290298461914e-09,
        "relative_error": 1.672426311095604e-16,
        "validation_passed": true
      },
      "params": {
        "sa_steps": 40000,
        "sa_T0": 5.0,
        "sa_Tend": 0.01,
        "sa_move_probs": {
          "premium": 0.075,
          "deductible": 0.075,
          "flip_other": 0.8500000000000001
        },
        "multistart": true,
        "num_starts": 20,
        "start_seed_policy": "seed_for_start = (base_seed*104729 + start_id*7919) mod 2^32",
        "random_seed_policy": "solver_rng_tied_to_instance_seed",
        "random_seed": 104729002,
        "convergence": {
          "best_found_at_step": 131,
          "convergence_fraction": 0.003275,
          "converged_early": true
        },
        "post_sa_hard_onehot_repair": true
      }
    }
  }
}