{
  "scenario": "S4_affordability",
  "scenario_file": "config_qubo_S4.yaml",
  "seed": 2000,
  "N": 200,
  "M": 4,
  "K": 5,
  "L_reg_slack": 5,
  "n_total": 214,
  "qubo_file_used": "qubo_Q_S4_affordability_N200.npz",
  "energy_greedy": -837954655.2791474,
  "energy_sa_best": -837960873.9905264,
  "objective_raw_greedy": 20107.77111461528,
  "objective_raw_sa_best": 13889.059735579049,
  "greedy_runtime_sec": 0.22411660000216216,
  "sa_runtime_sec": 25.58116489998065,
  "total_classical_runtime_sec": 25.80528149998281,
  "solvers": {
    "greedy": {
      "energy_total": -837954655.2791474,
      "raw_objective": 20107.77111461528,
      "decoded": {
        "chosen_deductible_band": 1,
        "chosen_premium_band": 1,
        "selected_features_count": 18,
        "selected_feature_ids": [
          2,
          12,
          20,
          21,
          31,
          39,
          46,
          50,
          68,
          99,
          105,
          110,
          116,
          125,
          157,
          166,
          168,
          182
        ],
        "selected_reg_features_count": 18
      },
      "violations": {
        "onehot_y": 0.0,
        "onehot_z": 0.0,
        "reg_shortfall": 0.0,
        "affordability_indicator": 0.0
      },
      "penalty_energy": {
        "penE_onehot": 0.0,
        "penE_reg": 0.0,
        "penE_afford": 0.0,
        "penE_total": 0.0
      },
      "constraint_checks": {
        "onehot_ok": true,
        "reg_satisfied": true,
        "reg_violation_amount": 0,
        "affordability_enabled": true,
        "affordability_disallow_bands": [
          4,
          5
        ],
        "affordability_satisfied": true,
        "affordability_violation": false,
        "is_feasible": true
      },
      "feasibility_margin": {
        "onehot_worst_violation": 0.0,
        "reg_shortfall": 0.0,
        "affordability_violated": false
      },
      "qubo_terms_signed": {
        "qterm_onehot_signed": -2578383.886308498,
        "qterm_reg_signed": -835396379.1639534,
        "qterm_afford_signed": 0.0,
        "qterm_total_signed": -837974763.050262
      },
      "penalty_weights": {
        "A_onehot": 1289191.943154249,
        "B_reg": 2578383.886308498,
        "D_afford": 257838388.6308498
      },
      "energy_decomposition_check": {
        "reconstructed_energy": -837954655.2791474,
        "absolute_error": 0.0,
        "relative_error": 0.0,
        "validation_passed": true
      },
      "params": {
        "multistart": true,
        "num_starts": 20,
        "random_seed": 209458001
      }
    },
    "sa": {
      "energy_total": -837960873.9905264,
      "raw_objective": 13889.059735579049,
      "decoded": {
        "chosen_deductible_band": 2,
        "chosen_premium_band": 3,
        "selected_features_count": 18,
        "selected_feature_ids": [
          2,
          20,
          39,
          50,
          57,
          64,
          68,
          76,
          88,
          105,
          116,
          135,
          144,
          157,
          168,
          175,
          192,
          195
        ],
        "selected_reg_features_count": 18
      },
      "violations": {
        "onehot_y": 0.0,
        "onehot_z": 0.0,
        "reg_shortfall": 0.0,
        "affordability_indicator": 0.0
      },
      "penalty_energy": {
        "penE_onehot": 0.0,
        "penE_reg": 0.0,
        "penE_afford": 0.0,
        "penE_total": 0.0
      },
      "constraint_checks": {
        "onehot_ok": true,
        "reg_satisfied": true,
        "reg_violation_amount": 0,
        "affordability_enabled": true,
        "affordability_disallow_bands": [
          4,
          5
        ],
        "affordability_satisfied": true,
        "affordability_violation": false,
        "is_feasible": true
      },
      "feasibility_margin": {
        "onehot_worst_violation": 0.0,
        "reg_shortfall": 0.0,
        "affordability_violated": false
      },
      "qubo_terms_signed": {
        "qterm_onehot_signed": -2578383.886308498,
        "qterm_reg_signed": -835396379.1639534,
        "qterm_afford_signed": 0.0,
        "qterm_total_signed": -837974763.050262
      },
      "penalty_weights": {
        "A_onehot": 1289191.943154249,
        "B_reg": 2578383.886308498,
        "D_afford": 257838388.6308498
      },
      "energy_decomposition_check": {
        "reconstructed_energy": -837960873.9905264,
        "absolute_error": 0.0,
        "relative_error": 0.0,
        "validation_passed": true
      },
      "params": {
        "sa_steps": 40000,
        "sa_T0": 5.0,
        "sa_Tend": 0.01,
        "sa_move_probs": {
          "premium": 0.075,
          "deductible": 0.075,
          "flip_other": 0.8500000000000001
        },
        "multistart": true,
        "num_starts": 20,
        "start_seed_policy": "seed_for_start = (base_seed*104729 + start_id*7919) mod 2^32",
        "random_seed_policy": "solver_rng_tied_to_instance_seed",
        "random_seed": 209458002,
        "convergence": {
          "best_found_at_step": 1222,
          "convergence_fraction": 0.03055,
          "converged_early": true
        },
        "post_sa_hard_onehot_repair": true
      }
    }
  }
}