{
  "scenario": "S2_risk_adjusted",
  "scenario_file": "config_qubo_S2.yaml",
  "seed": 2008,
  "N": 150,
  "M": 4,
  "K": 5,
  "L_reg_slack": 4,
  "n_total": 163,
  "qubo_file_used": "qubo_Q_S2_risk_adjusted_N150.npz",
  "energy_greedy": -407370389.8665389,
  "energy_sa_best": -407981766.46294665,
  "raw_objective_greedy": 5921674.667273979,
  "raw_objective_sa_best": 5310298.0708662905,
  "greedy_runtime_sec": 0.25131099999999995,
  "sa_runtime_sec": 25.5683148,
  "total_classical_runtime_sec": 25.8196258,
  "solvers": {
    "greedy": {
      "energy_total": -407370389.8665389,
      "raw_objective": 5921674.667273979,
      "decoded": {
        "chosen_deductible_band": 2,
        "chosen_premium_band": 2,
        "selected_features_count": 14,
        "selected_feature_ids": [
          26,
          27,
          46,
          53,
          58,
          66,
          95,
          103,
          110,
          119,
          126,
          129,
          135,
          142
        ],
        "selected_reg_features_count": 14
      },
      "violations": {
        "onehot_y": 0.0,
        "onehot_z": 0.0,
        "reg_shortfall": 0.0,
        "affordability_indicator": 0.0
      },
      "penalty_energy": {
        "penE_onehot": 0.0,
        "penE_reg": 0.0,
        "penE_afford": 0.0,
        "penE_total": 0.0
      },
      "constraint_checks": {
        "onehot_ok": true,
        "reg_satisfied": true,
        "reg_violation_amount": 0,
        "affordability_enabled": false,
        "affordability_disallow_bands": [],
        "affordability_satisfied": true,
        "affordability_violation": false,
        "is_feasible": true
      },
      "feasibility_margin": {
        "onehot_worst_violation": 0.0,
        "reg_shortfall": 0.0,
        "affordability_violated": false
      },
      "qubo_terms_signed": {
        "qterm_onehot_signed": -2097929.26159296,
        "qterm_reg_signed": -411194135.27222013,
        "qterm_afford_signed": 0.0,
        "qterm_total_signed": -413292064.5338131
      },
      "penalty_weights": {
        "A_onehot": 1048964.63079648,
        "B_reg": 2097929.26159296,
        "D_afford": 0.0
      },
      "energy_decomposition_check": {
        "reconstructed_energy": -407370389.8665391,
        "absolute_error": 2.384185791015625e-07,
        "relative_error": 5.85262417279941e-16,
        "validation_passed": true
      },
      "params": {
        "multistart": true,
        "num_starts": 20,
        "random_seed": 210295833
      }
    },
    "sa": {
      "energy_total": -407981766.46294665,
      "raw_objective": 5310298.0708662905,
      "decoded": {
        "chosen_deductible_band": 2,
        "chosen_premium_band": 5,
        "selected_features_count": 14,
        "selected_feature_ids": [
          26,
          46,
          53,
          58,
          66,
          68,
          83,
          95,
          103,
          110,
          119,
          129,
          142,
          149
        ],
        "selected_reg_features_count": 14
      },
      "violations": {
        "onehot_y": 0.0,
        "onehot_z": 0.0,
        "reg_shortfall": 0.0,
        "affordability_indicator": 0.0
      },
      "penalty_energy": {
        "penE_onehot": 0.0,
        "penE_reg": 0.0,
        "penE_afford": 0.0,
        "penE_total": 0.0
      },
      "constraint_checks": {
        "onehot_ok": true,
        "reg_satisfied": true,
        "reg_violation_amount": 0,
        "affordability_enabled": false,
        "affordability_disallow_bands": [],
        "affordability_satisfied": true,
        "affordability_violation": false,
        "is_feasible": true
      },
      "feasibility_margin": {
        "onehot_worst_violation": 0.0,
        "reg_shortfall": 0.0,
        "affordability_violated": false
      },
      "qubo_terms_signed": {
        "qterm_onehot_signed": -2097929.26159296,
        "qterm_reg_signed": -411194135.27222013,
        "qterm_afford_signed": 0.0,
        "qterm_total_signed": -413292064.5338131
      },
      "penalty_weights": {
        "A_onehot": 1048964.63079648,
        "B_reg": 2097929.26159296,
        "D_afford": 0.0
      },
      "energy_decomposition_check": {
        "reconstructed_energy": -407981766.46294683,
        "absolute_error": 1.7881393432617188e-07,
        "relative_error": 4.382890340331225e-16,
        "validation_passed": true
      },
      "params": {
        "sa_steps": 40000,
        "sa_T0": 5.0,
        "sa_Tend": 0.01,
        "sa_move_probs": {
          "premium": 0.075,
          "deductible": 0.075,
          "flip_other": 0.8500000000000001
        },
        "multistart": true,
        "num_starts": 20,
        "start_seed_policy": "seed_for_start = (base_seed*104729 + start_id*7919) mod 2^32",
        "random_seed_policy": "solver_rng_tied_to_instance_seed",
        "random_seed": 210295834,
        "convergence": {
          "best_found_at_step": 856,
          "convergence_fraction": 0.0214,
          "converged_early": true
        },
        "post_sa_hard_onehot_repair": true
      }
    }
  }
}